OpenOrchestrator/__init__.py
OpenOrchestrator/__main__.py
OpenOrchestrator/common/__init__.py
OpenOrchestrator/common/connection_frame.py
OpenOrchestrator/common/crypto_util.py
OpenOrchestrator/common/datetime_util.py
OpenOrchestrator/database/__init__.py
OpenOrchestrator/database/base.py
OpenOrchestrator/database/constants.py
OpenOrchestrator/database/db_util.py
OpenOrchestrator/database/logs.py
OpenOrchestrator/database/queues.py
OpenOrchestrator/database/schedulers.py
OpenOrchestrator/database/triggers.py
OpenOrchestrator/database/truncated_string.py
OpenOrchestrator/orchestrator/__init__.py
OpenOrchestrator/orchestrator/application.py
OpenOrchestrator/orchestrator/datetime_input.py
OpenOrchestrator/orchestrator/test_helper.py
OpenOrchestrator/orchestrator/popups/__init__.py
OpenOrchestrator/orchestrator/popups/constant_popup.py
OpenOrchestrator/orchestrator/popups/credential_popup.py
OpenOrchestrator/orchestrator/popups/generic_popups.py
OpenOrchestrator/orchestrator/popups/trigger_popup.py
OpenOrchestrator/orchestrator/tabs/constants_tab.py
OpenOrchestrator/orchestrator/tabs/logging_tab.py
OpenOrchestrator/orchestrator/tabs/queue_tab.py
OpenOrchestrator/orchestrator/tabs/schedulers_tab.py
OpenOrchestrator/orchestrator/tabs/settings_tab.py
OpenOrchestrator/orchestrator/tabs/trigger_tab.py
OpenOrchestrator/orchestrator_connection/__init__.py
OpenOrchestrator/orchestrator_connection/connection.py
OpenOrchestrator/scheduler/__init__.py
OpenOrchestrator/scheduler/application.py
OpenOrchestrator/scheduler/run_tab.py
OpenOrchestrator/scheduler/runner.py
OpenOrchestrator/scheduler/settings_tab.py
OpenOrchestrator/scheduler/util.py
OpenOrchestrator/tests/__init__.py
OpenOrchestrator/tests/db_test_util.py
OpenOrchestrator/tests/test_db_util.py
OpenOrchestrator/tests/test_orchestrator_connection.py
OpenOrchestrator/tests/test_trigger_polling.py
OpenOrchestrator/tests/ui_tests/__init__.py
OpenOrchestrator/tests/ui_tests/test_constants_tab.py
openorchestrator-2.0.1.dist-info/licenses/LICENSE
openorchestrator-2.0.1.dist-info/METADATA
openorchestrator-2.0.1.dist-info/WHEEL
openorchestrator-2.0.1.dist-info/top_level.txt
openorchestrator-2.0.1.dist-info/RECORD
