Metadata-Version: 2.4
Name: OpenOrchestrator
Version: 2.0.1
Summary: A package containing OpenOrchestrator and OpenOrchestrator Scheduler
Author-email: ITK Development <itk-rpa@mkb.aarhus.dk>
Project-URL: Homepage, https://github.com/itk-dev-rpa/OpenOrchestrator
Project-URL: Bug Tracker, https://github.com/itk-dev-rpa/OpenOrchestrator/issues
Classifier: Programming Language :: Python :: 3
Classifier: License :: OSI Approved :: MIT License
Classifier: Operating System :: Microsoft :: Windows
Requires-Python: >=3.11
License-File: LICENSE
Requires-Dist: cryptography==45.0.*
Requires-Dist: cronsim==2.6
Requires-Dist: SQLAlchemy==2.0.*
Requires-Dist: pyodbc==5.2.*
Requires-Dist: nicegui==2.22.*
Provides-Extra: dev
Requires-Dist: pylint; extra == "dev"
Requires-Dist: flake8; extra == "dev"
Requires-Dist: selenium; extra == "dev"
Provides-Extra: alembic
Requires-Dist: alembic==1.16.*; extra == "alembic"
Dynamic: license-file
